generic_json_encoders/__about__.py
generic_json_encoders/__init__.py
generic_json_encoders/base.py
generic_json_encoders/lilya_monkey_patcher.py
generic_json_encoders-0.0.2.dist-info/METADATA
generic_json_encoders-0.0.2.dist-info/WHEEL
generic_json_encoders-0.0.2.dist-info/licenses/LICENSE.txt
generic_json_encoders-0.0.2.dist-info/RECORD
