Metadata-Version: 2.3
Name: generic-json-encoders
Version: 0.0.2
Project-URL: Documentation, https://github.com/devkral/generic-json-encoders#readme
Project-URL: Issues, https://github.com/devkral/generic-json-encoders/issues
Project-URL: Source, https://github.com/devkral/generic-json-encoders
Author-email: alex <devkral@web.de>
License: Copyright © 2024, devkral@web.de. All rights reserved.
Keywords: encoders,esmerald,lilya
Classifier: Development Status :: 4 - Beta
Classifier: Intended Audience :: Developers
Classifier: License :: OSI Approved :: BSD License
Classifier: Programming Language :: Python
Classifier: Programming Language :: Python :: 3.8
Classifier: Programming Language :: Python :: 3.9
Classifier: Programming Language :: Python :: 3.10
Classifier: Programming Language :: Python :: 3.11
Classifier: Programming Language :: Python :: 3.12
Classifier: Programming Language :: Python :: Implementation :: CPython
Classifier: Programming Language :: Python :: Implementation :: PyPy
Requires-Python: >=3.9
Requires-Dist: orjson
